    {
    "$schema": "https://schema.management.azure.com/schemas/2015-01-01/deploymentParameters.json#",
    "contentVersion": "1.0.0.0",
    "parameters": {
        "vmAdminUsername": {
            "value": "VMAdmin"
          },
          "vmAdminPassword": {
            "value": "VMP@ssw0rd"
          },
          "vmDnsLabelPrefix": {
            "value": "aksvmname"
          },
          "vmSize": {
            "value": "Standard_D2_v2"
          },
          "vmOsVersion": {
            "value": "2016-Datacenter"
          },
          "vmInitscriptUrl": {
            "value": "https://raw.githubusercontent.com/flecoqui/TestCppCustomMetricPrometheusClient/master/101-aks-vnet-vm/install-tsroute.ps1"
          },
          "vmInitScriptFileName": {
            "value": "install-tsroute.ps1"
          },        
        "aksResourceName": {
            "value": "akstest"
        },
        "aksDnsPrefix": {
            "value": "aksvnetvm"
        },
        "aksOsDiskSizeGB": {
            "value": 0
        },
        "aksAgentCount": {
            "value": 1
        },
        "aksAgentVMSize": {
            "value": "Standard_D2_v2"
        },
        "aksServicePrincipalClientId": {
            "value": "bd28006a-272c-43a5-bd80-5bafc49e9144"
        },
        "aksServicePrincipalClientSecret": {
            "value": "a27ed361-59db-46d5-b91f-fc6c5c45e43e"
        },
        "aksKubernetesVersion": {
            "value": "1.10.12"
        },
        "aksNetworkPlugin": {
            "value": "azure"
        },
        "aksMaxPods": {
            "value": 30
        },
        "aksEnableRBAC": {
            "value": true
        }
    }
}
